webots_web_log_interface/interface.py
webots_web_log_interface-0.2.5.dist-info/LICENSE
webots_web_log_interface-0.2.5.dist-info/WHEEL
webots_web_log_interface-0.2.5.dist-info/METADATA
webots_web_log_interface-0.2.5.dist-info/RECORD
