Metadata-Version: 2.1
Name: webots-web-log-interface
Version: 0.2.5
Summary: A python library used to interact with webots robocup game web logs
Home-page: https://bit-bots.github.io/webots-web-log-interface
License: MIT
Keywords: webots,logs
Author: Florian Vahl
Author-email: florian@flova.de
Requires-Python: >=3.7,<3.11
Classifier: License :: OSI Approved :: MIT License
Classifier: Programming Language :: Python :: 3
Classifier: Programming Language :: Python :: 3.10
Classifier: Programming Language :: Python :: 3.7
Classifier: Programming Language :: Python :: 3.8
Classifier: Programming Language :: Python :: 3.9
Requires-Dist: matplotlib (>=3.4.3,<4.0.0)
Requires-Dist: numpy (>=1.21.3,<2.0.0)
Project-URL: Documentation, https://bit-bots.github.io/webots-web-log-interface/html/webots_web_log_interface
Project-URL: Repository, https://github.com/bit-bots/webots-web-log-interface
